odoo/addons/task_project_status/README.rst
odoo/addons/task_project_status/__init__.py
odoo/addons/task_project_status/__manifest__.py
odoo/addons/task_project_status/i18n/es.po
odoo/addons/task_project_status/i18n/it.po
odoo/addons/task_project_status/i18n/task_project_status.pot
odoo/addons/task_project_status/models/__init__.py
odoo/addons/task_project_status/models/project.py
odoo/addons/task_project_status/readme/CONTRIBUTORS.rst
odoo/addons/task_project_status/readme/DESCRIPTION.rst
odoo/addons/task_project_status/static/description/icon.png
odoo/addons/task_project_status/static/description/index.html
odoo/addons/task_project_status/tests/__init__.py
odoo/addons/task_project_status/tests/task_project_status.py
odoo/addons/task_project_status/tests/test_task_project_status.py
odoo/addons/task_project_status/views/project_view.xml
odoo_addon_task_project_status-16.0.1.0.0.3.dist-info/METADATA
odoo_addon_task_project_status-16.0.1.0.0.3.dist-info/WHEEL
odoo_addon_task_project_status-16.0.1.0.0.3.dist-info/top_level.txt
odoo_addon_task_project_status-16.0.1.0.0.3.dist-info/RECORD
